core/__init__.py
core/extract/__init__.py
core/extract/base.py
core/extract/postgres.py
core/load/__init__.py
core/load/base.py
core/load/elasticsearch.py
core/load/opensearch.py
core/load/pinecone.py
core/load/qdrant.py
core/load/tests/test_pinecone.py
core/load/tests/test_qdrant.py
core/load/weaviate.py
core/sdk/__init__.py
core/sdk/embedding.py
core/sdk/pipeline.py
core/sdk/realtime.py
core/sdk/sink.py
core/sdk/source.py
core/sdk/target.py
core/sdk/transform.py
core/sdk/types.py
core/transform/__init__.py
core/transform/base.py
core/transform/cohere.py
core/transform/custom.py
core/transform/openai.py
core/transform/sentence_transformers.py
core/transform/tests/test_cohere.py
core/transform/tests/test_custom.py
core/transform/tests/test_openai.py
core/transform/tests/test_sentence_transformers.py
retake/__init__.py
streams/__init__.py
streams/app.py
retake-0.1.14.dist-info/LICENSE
retake-0.1.14.dist-info/METADATA
retake-0.1.14.dist-info/WHEEL
retake-0.1.14.dist-info/RECORD
