Metadata-Version: 2.1
Name: retake
Version: 0.1.14
Summary: Open Source Infrastructure for Vector Data Streams
Author: Ming Ying
Author-email: ming.ying.nyc@gmail.com
Requires-Python: >=3.9,<3.12
Classifier: Programming Language :: Python :: 3
Classifier: Programming Language :: Python :: 3.9
Classifier: Programming Language :: Python :: 3.10
Classifier: Programming Language :: Python :: 3.11
Requires-Dist: cohere (>=4.12.0,<5.0.0)
Requires-Dist: confluent-kafka (>=2.2.0,<3.0.0)
Requires-Dist: elasticsearch (>=8.8.2,<9.0.0)
Requires-Dist: fastavro (>=1.8.0,<2.0.0)
Requires-Dist: faust-streaming (>=0.10.14,<0.11.0)
Requires-Dist: gotrue (>=1.0.1,<2.0.0)
Requires-Dist: httpx (>=0.23.0,<0.24.0)
Requires-Dist: openai (>=0.27.8,<0.28.0)
Requires-Dist: opensearch-py (>=2.2.0,<3.0.0)
Requires-Dist: pinecone-client (>=2.2.2,<3.0.0)
Requires-Dist: psycopg2-binary (>=2.9.6,<3.0.0)
Requires-Dist: pydantic (>=1.8.0,<2.0.0)
Requires-Dist: python-dotenv (>=1.0.0,<2.0.0)
Requires-Dist: qdrant-client (>=1.3.1,<2.0.0)
Requires-Dist: requests (>=2.31.0,<3.0.0)
Requires-Dist: sentence-transformers (>=2.2.2,<3.0.0)
Requires-Dist: tqdm (>=4.65.0,<5.0.0)
Requires-Dist: types-psycopg2 (>=2.9.21.10,<3.0.0.0)
Requires-Dist: types-tqdm (>=4.65.0.1,<5.0.0.0)
Requires-Dist: weaviate-client (>=3.22.1,<4.0.0)
